odoo/addons/shopinvader_delivery_carrier/README.rst
odoo/addons/shopinvader_delivery_carrier/__init__.py
odoo/addons/shopinvader_delivery_carrier/__manifest__.py
odoo/addons/shopinvader_delivery_carrier/controllers/__init__.py
odoo/addons/shopinvader_delivery_carrier/controllers/main.py
odoo/addons/shopinvader_delivery_carrier/data/cart_step.xml
odoo/addons/shopinvader_delivery_carrier/demo/backend_demo.xml
odoo/addons/shopinvader_delivery_carrier/demo/mail_template.xml
odoo/addons/shopinvader_delivery_carrier/demo/shopinvader_notification.xml
odoo/addons/shopinvader_delivery_carrier/i18n/shopinvader_delivery_carrier.pot
odoo/addons/shopinvader_delivery_carrier/models/__init__.py
odoo/addons/shopinvader_delivery_carrier/models/backend.py
odoo/addons/shopinvader_delivery_carrier/models/delivery_carrier.py
odoo/addons/shopinvader_delivery_carrier/models/sale.py
odoo/addons/shopinvader_delivery_carrier/models/shopinvader_notification.py
odoo/addons/shopinvader_delivery_carrier/models/stock_picking.py
odoo/addons/shopinvader_delivery_carrier/readme/CONTRIBUTORS.rst
odoo/addons/shopinvader_delivery_carrier/readme/DESCRIPTION.rst
odoo/addons/shopinvader_delivery_carrier/readme/USAGE.rst
odoo/addons/shopinvader_delivery_carrier/services/__init__.py
odoo/addons/shopinvader_delivery_carrier/services/abstract_sale.py
odoo/addons/shopinvader_delivery_carrier/services/cart.py
odoo/addons/shopinvader_delivery_carrier/services/delivery.py
odoo/addons/shopinvader_delivery_carrier/services/delivery_carrier.py
odoo/addons/shopinvader_delivery_carrier/static/description/icon.png
odoo/addons/shopinvader_delivery_carrier/static/description/index.html
odoo/addons/shopinvader_delivery_carrier/tests/__init__.py
odoo/addons/shopinvader_delivery_carrier/tests/common.py
odoo/addons/shopinvader_delivery_carrier/tests/test_carrier.py
odoo/addons/shopinvader_delivery_carrier/tests/test_delivery_carrier.py
odoo/addons/shopinvader_delivery_carrier/tests/test_delivery_service.py
odoo12_addon_shopinvader_delivery_carrier-12.0.3.1.2.dist-info/METADATA
odoo12_addon_shopinvader_delivery_carrier-12.0.3.1.2.dist-info/WHEEL
odoo12_addon_shopinvader_delivery_carrier-12.0.3.1.2.dist-info/top_level.txt
odoo12_addon_shopinvader_delivery_carrier-12.0.3.1.2.dist-info/RECORD
