Metadata-Version: 2.1
Name: odoo12-addon-shopinvader-delivery-carrier
Version: 12.0.3.1.2
Summary: Carrier integration for Shopinvader
Home-page: https://github.com/shopinvader/odoo-shopinvader
Author: Akretion
License: AGPL-3
Platform: UNKNOWN
Classifier: Programming Language :: Python
Classifier: Framework :: Odoo
Classifier: License :: OSI Approved :: GNU Affero General Public License v3
Requires-Python: >=3.5
Requires-Dist: odoo12-addon-delivery-carrier-info
Requires-Dist: odoo12-addon-queue-job
Requires-Dist: odoo12-addon-sale-shipping-info-helper
Requires-Dist: odoo12-addon-shopinvader
Requires-Dist: odoo (<12.1dev,>=12.0a)
